{
    "title": "Parsippany -Troy Hills STEM Pathways",
    "outline": [
        {
            "level": "H3",
            "text": "experience.",
            "page": 1
        },
        {
            "level": "H2",
            "text": "PATHWAY OPTIONS",
            "page": 1
        },
        {
            "level": "H2",
            "text": "REGULAR PATHWAY",
            "page": 1
        },
        {
            "level": "H1",
            "text": "DISTINCTION PATHWAY",
            "page": 1
        },
        {
            "level": "H2",
            "text": "Goals:",
            "page": 1
        },
        {
            "level": "H3",
            "text": "Computer Science/",
            "page": 2
        },
        {
            "level": "H3",
            "text": "Applied",
            "page": 2
        },
        {
            "level": "H3",
            "text": "Technology/",
            "page": 2
        },
        {
            "level": "H3",
            "text": "Family Consumer",
            "page": 2
        },
        {
            "level": "H3",
            "text": "Science and Other",
            "page": 2
        },
        {
            "level": "H3",
            "text": "Photography",
            "page": 2
        },
        {
            "level": "H3",
            "text": "Design",
            "page": 2
        },
        {
            "text": "Parsippany -Troy Hills STEM Pathways",
            "level": "H1",
            "page": 0
        },
        {
            "text": "PATHWAY OPTIONS",
            "level": "H2",
            "page": 0
        },
        {
            "text": "REGULAR PATHWAY",
            "level": "H2",
            "page": 0
        },
        {
            "text": "DISTINCTION PATHWAY",
            "level": "H2",
            "page": 0
        },
        {
            "text": "Elective Course Offerings",
            "level": "H2",
            "page": 1
        },
        {
            "text": "Computer Science/",
            "level": "H3",
            "page": 1
        },
        {
            "text": "Family Consumer",
            "level": "H3",
            "page": 1
        },
        {
            "text": "Science and Other",
            "level": "H3",
            "page": 1
        },
        {
            "text": "What Colleges Say!",
            "level": "H3",
            "page": 1
        },
        {
            "text": "For more information and our application please visit our website by clicking here.",
            "level": "H3",
            "page": 1
        }
    ]
}